line_works/__init__.py
line_works/client.py
line_works/config.py
line_works/decorator.py
line_works/exceptions.py
line_works/logger.py
line_works/tracer.py
line_works/enums/__init__.py
line_works/enums/message_type.py
line_works/enums/yes_no_option.py
line_works/models/__init__.py
line_works/models/emoji.py
line_works/models/mention.py
line_works/models/substitution.py
line_works/mqtt/__init__.py
line_works/mqtt/client.py
line_works/mqtt/config.py
line_works/mqtt/exceptions.py
line_works/mqtt/packets.py
line_works/mqtt/enums/__init__.py
line_works/mqtt/enums/channel_type.py
line_works/mqtt/enums/connection_status.py
line_works/mqtt/enums/control_packet_type.py
line_works/mqtt/enums/message_type.py
line_works/mqtt/enums/notification_sub_type.py
line_works/mqtt/enums/notification_type.py
line_works/mqtt/enums/packet_type.py
line_works/mqtt/enums/presence.py
line_works/mqtt/enums/service_sub_type.py
line_works/mqtt/enums/service_type.py
line_works/mqtt/enums/voip_termination_type.py
line_works/mqtt/models/__init__.py
line_works/mqtt/models/packet.py
line_works/mqtt/models/payload/__init__.py
line_works/mqtt/models/payload/_base.py
line_works/mqtt/models/payload/badge.py
line_works/mqtt/models/payload/message.py
line_works/mqtt/models/payload/service.py
line_works/openapi/__init__.py
line_works/openapi/storage/__init__.py
line_works/openapi/storage/api_client.py
line_works/openapi/storage/api_response.py
line_works/openapi/storage/configuration.py
line_works/openapi/storage/exceptions.py
line_works/openapi/storage/py.typed
line_works/openapi/storage/rest.py
line_works/openapi/storage/api/__init__.py
line_works/openapi/storage/api/default_api.py
line_works/openapi/storage/models/__init__.py
line_works/openapi/storage/models/resource_extras.py
line_works/openapi/storage/models/upload_resouce_response.py
line_works/openapi/storage/models/upload_resource_reponse_result.py
line_works/openapi/talk/__init__.py
line_works/openapi/talk/api_client.py
line_works_sdk-3.8.dist-info/METADATA
line_works_sdk-3.8.dist-info/WHEEL
line_works_sdk-3.8.dist-info/top_level.txt
line_works_sdk-3.8.dist-info/RECORD
