Metadata-Version: 2.4
Name: line-works-sdk
Version: 3.8
Summary: LINE Works SDK for Python
Home-page: https://github.com/nanato12/line-works-sdk
Author: nanato12
Author-email: admin@okj.info
Maintainer: nanato12
Maintainer-email: admin@okj.info
License: MIT License
Keywords: line line-works works
Classifier: License :: OSI Approved :: MIT License
Classifier: Intended Audience :: Developers
Classifier: Programming Language :: Python :: 3
Classifier: Programming Language :: Python :: 3 :: Only
Classifier: Programming Language :: Python :: 3.10
Classifier: Programming Language :: Python :: 3.11
Classifier: Programming Language :: Python :: 3.12
Classifier: Topic :: Software Development
Requires-Python: >=3.10
Requires-Dist: pydantic>=2.9.2
Requires-Dist: pydantic_core>=2.23.4
Requires-Dist: requests>=2.32.3
Requires-Dist: websockets>=14.2
Requires-Dist: urllib3<3.0.0,>=1.25.3
Requires-Dist: python_dateutil>=2.8.2
Requires-Dist: typing-extensions>=4.7.1
Requires-Dist: pillow==12.0.0
